MANIFEST.in
setup.cfg
setup.py
lgt/common/python/lgt_logging.py
lgt/common/python/pubsub/.gitignore
lgt/common/python/pubsub/__init__.py
lgt/common/python/pubsub/env.py
lgt/common/python/pubsub/messages.py
lgt/common/python/pubsub/pubsubfactory.py
lgt/common/python/pubsub/requirements.txt
lgt/common/python/slack_client/.gitignore
lgt/common/python/slack_client/__init__.py
lgt/common/python/slack_client/methods.py
lgt/common/python/slack_client/requirements.txt
lgt/common/python/slack_client/slack_client.py
lgt/common/python/slack_client/web_client.py
lgt_common.egg-info/PKG-INFO
lgt_common.egg-info/SOURCES.txt
lgt_common.egg-info/dependency_links.txt
lgt_common.egg-info/not-zip-safe
lgt_common.egg-info/requires.txt
lgt_common.egg-info/top_level.txt