Metadata-Version: 1.0
Name: lgt-common
Version: 3.0
Summary: LGT common builds
Home-page: UNKNOWN
Author: UNKNOWN
Author-email: alexander.grin1997@gmail.com
License: UNKNOWN
Platform: UNKNOWN
